Ej1/1bit/Ej1A.v
module Ej1A(D,clk,Q,rst,en);
input wire D;
input wire clk;
input wire rst;
input wire en;
output reg Q;
always @(posedge clk)
begin
  if (rst == 1) begin
    Q <= 0;
  end else if (rst == 0) begin
    if (en == 0) begin
      Q <= 0;
    end else if (en == 1) begin
      Q <= D;
    end
  end
end
endmodule

Ej1/1bit/Ej1A_tb.v

module Ej1A_tb();
reg D;
reg clk;
reg rst;
reg en;
wire Q;

Ej1A U1(D,clk,Q,rst,en);

always begin
clk = 1;
#1 clk<=~clk;
end
initial begin
$display("Clk1bit");
    $display("rst en clk | D Q");
    $display("------------------------------");
    $monitor("%b %b %b | %b %b", rst, en, clk, D, Q);
  end
initial begin
 rst=1; en = 0;
 D <= 0;
 #5;
 D <= 1;
 #5;
 en = 1;
 D <= 0;
 #5;
 D <= 1;
 #5
 rst=0; en = 0;
 D <= 0;
 #5;
 D <= 1;
 #5;
 en = 1;
 D <= 0;
 #5;
 D <= 1;
end



initial
    #40 $finish;
  initial begin
    $dumpfile("Ej1A_tb.vcd");
    $dumpvars(0,Ej1A_tb);
  end
endmodule

Ej1/1bit/Ej1A_tb.vcd
$date
	Thu Oct 29 11:32:19 2020
$end
$version
	Icarus Verilog
$end
$timescale
	1ps
$end
$scope module Ej1A_tb $end
$var wire 1 ! Q $end
$var reg 1 " D $end
$var reg 1 # clk $end
$var reg 1 $ en $end
$var reg 1 % rst $end
$scope module U1 $end
$var wire 1 " D $end
$var wire 1 # clk $end
$var wire 1 $ en $end
$var wire 1 % rst $end
$var reg 1 ! Q $end
$upscope $end
$upscope $end
$enddefinitions $end
#0
$dumpvars
1%
0$
1#
0"
0!
$end
#1
0#
#2
1#
#3
0#
#4
1#
#5
0#
1"
#6
1#
#7
0#
#8
1#
#9
0#
#10
0"
1#
1$
#11
0#
#12
1#
#13
0#
#14
1#
#15
0#
1"
#16
1#
#17
0#
#18
1#
#19
0#
#20
0"
1#
0$
0%
#21
0#
#22
1#
#23
0#
#24
1#
#25
0#
1"
#26
1#
#27
0#
#28
1#
#29
0#
#30
1!
0"
1#
1$
#31
0#
#32
0!
1#
#33
0#
#34
1#
#35
0#
1"
#36
1!
1#
