Ej1/4bit/EJ14bit.v
module EJ14bit(D,clk,Q,rst,en);
input wire [3:0] D;
input wire clk;
input wire rst;
input wire en;
output reg [3:0] Q;
always @(posedge clk)
begin
  if (rst == 1) begin
    Q <= 4'b0000;
  end else if (rst == 0) begin
    if (en == 0) begin
      Q <= 4'b0000;
    end else if (en == 1) begin
      Q <= D;
    end
  end
end
endmodule

Ej1/4bit/EJ14bit_tb.v
module EJ14bit_tb();
reg [3:0]D;
reg clk;
reg rst;
reg en;
wire [3:0]Q;

EJ14bit U1(D,clk,Q,rst,en);

always begin
clk = 1;
#1 clk<=~clk;
end
initial begin
$display("Clk1bit");
    $display("rst en clk | D Q");
    $display("------------------------------");
    $monitor("%b %b %b | %b %b", rst, en, clk, D, Q);
  end
initial begin
 rst=1; en = 0; D <= 4'b0000;
 #5 D <= 4'b0001;
 #5 D <= 4'b10;
 #5 D <= 4'b11;
 #5 D <= 4'b100;
 #5 D <= 4'b101;
 #5 D <= 4'b110;
 #5 D <= 4'b111;
 #5 D <= 4'b1000;
 #5 D <= 4'b1001;
 #5 D <= 4'b1010;
 #5 D <= 4'b1011;
 #5 D <= 4'b1100;
 #5 D <= 4'b1101;
 #5 D <= 4'b1110;
 #5 D <= 4'b1111;
 #5 en = 1; D <= 4'b0000;
 #5 D <= 4'b0001;
 #5 D <= 4'b10;
 #5 D <= 4'b11;
 #5 D <= 4'b100;
 #5 D <= 4'b101;
 #5 D <= 4'b110;
 #5 D <= 4'b111;
 #5 D <= 4'b1000;
 #5 D <= 4'b1001;
 #5 D <= 4'b1010;
 #5 D <= 4'b1011;
 #5 D <= 4'b1100;
 #5 D <= 4'b1101;
 #5 D <= 4'b1110;
 #5 D <= 4'b1111;
 #5 rst=0; en = 0; D <= 4'b0000;
 #5 D <= 4'b0001;
 #5 D <= 4'b10;
 #5 D <= 4'b11;
 #5 D <= 4'b100;
 #5 D <= 4'b101;
 #5 D <= 4'b110;
 #5 D <= 4'b111;
 #5 D <= 4'b1000;
 #5 D <= 4'b1001;
 #5 D <= 4'b1010;
 #5 D <= 4'b1011;
 #5 D <= 4'b1100;
 #5 D <= 4'b1101;
 #5 D <= 4'b1110;
 #5 D <= 4'b1111;
 #5 en = 1; D <= 4'b0000;
 #5 D <= 4'b0001;
 #5 D <= 4'b10;
 #5 D <= 4'b11;
 #5 D <= 4'b100;
 #5 D <= 4'b101;
 #5 D <= 4'b110;
 #5 D <= 4'b111;
 #5 D <= 4'b1000;
 #5 D <= 4'b1001;
 #5 D <= 4'b1010;
 #5 D <= 4'b1011;
 #5 D <= 4'b1100;
 #5 D <= 4'b1101;
 #5 D <= 4'b1110;
 #5 D <= 4'b1111;

end



initial
    #320 $finish;
  initial begin
    $dumpfile("EJ14bit_tb.vcd");
    $dumpvars(0,EJ14bit_tb);
  end
endmodule

Ej1/4bit/EJ14bit_tb.vcd
$date
	Thu Oct 29 12:00:47 2020
$end
$version
	Icarus Verilog
$end
$timescale
	1ps
$end
$scope module EJ14bit_tb $end
$var wire 4 ! Q [3:0] $end
$var reg 4 " D [3:0] $end
$var reg 1 # clk $end
$var reg 1 $ en $end
$var reg 1 % rst $end
$scope module U1 $end
$var wire 4 & D [3:0] $end
$var wire 1 # clk $end
$var wire 1 $ en $end
$var wire 1 % rst $end
$var reg 4 ' Q [3:0] $end
$upscope $end
$upscope $end
$enddefinitions $end
#0
$dumpvars
b0 '
b0 &
1%
0$
1#
b0 "
b0 !
$end
#1
0#
#2
1#
#3
0#
#4
1#
#5
0#
b1 "
b1 &
#6
1#
#7
0#
#8
1#
#9
0#
#10
b10 "
b10 &
1#
#11
0#
#12
1#
#13
0#
#14
1#
#15
0#
b11 "
b11 &
#16
1#
#17
0#
#18
1#
#19
0#
#20
b100 "
b100 &
1#
#21
0#
#22
1#
#23
0#
#24
1#
#25
0#
b101 "
b101 &
#26
1#
#27
0#
#28
1#
#29
0#
#30
b110 "
b110 &
1#
#31
0#
#32
1#
#33
0#
#34
1#
#35
0#
b111 "
b111 &
#36
1#
#37
0#
#38
1#
#39
0#
#40
b1000 "
b1000 &
1#
#41
0#
#42
1#
#43
0#
#44
1#
#45
0#
b1001 "
b1001 &
#46
1#
#47
0#
#48
1#
#49
0#
#50
b1010 "
b1010 &
1#
#51
0#
#52
1#
#53
0#
#54
1#
#55
0#
b1011 "
b1011 &
#56
1#
#57
0#
#58
1#
#59
0#
#60
b1100 "
b1100 &
1#
#61
0#
#62
1#
#63
0#
#64
1#
#65
0#
b1101 "
b1101 &
#66
1#
#67
0#
#68
1#
#69
0#
#70
b1110 "
b1110 &
1#
#71
0#
#72
1#
#73
0#
#74
1#
#75
0#
b1111 "
b1111 &
#76
1#
#77
0#
#78
1#
#79
0#
#80
b0 "
b0 &
1#
1$
#81
0#
#82
1#
#83
0#
#84
1#
#85
0#
b1 "
b1 &
#86
1#
#87
0#
#88
1#
#89
0#
#90
b10 "
b10 &
1#
#91
0#
#92
1#
#93
0#
#94
1#
#95
0#
b11 "
b11 &
#96
1#
#97
0#
#98
1#
#99
0#
#100
b100 "
b100 &
1#
#101
0#
#102
1#
#103
0#
#104
1#
#105
0#
b101 "
b101 &
#106
1#
#107
0#
#108
1#
#109
0#
#110
b110 "
b110 &
1#
#111
0#
#112
1#
#113
0#
#114
1#
#115
0#
b111 "
b111 &
#116
1#
#117
0#
#118
1#
#119
0#
#120
b1000 "
b1000 &
1#
#121
0#
#122
1#
#123
0#
#124
1#
#125
0#
b1001 "
b1001 &
#126
1#
#127
0#
#128
1#
#129
0#
#130
b1010 "
b1010 &
1#
#131
0#
#132
1#
#133
0#
#134
1#
#135
0#
b1011 "
b1011 &
#136
1#
#137
0#
#138
1#
#139
0#
#140
b1100 "
b1100 &
1#
#141
0#
#142
1#
#143
0#
#144
1#
#145
0#
b1101 "
b1101 &
#146
1#
#147
0#
#148
1#
#149
0#
#150
b1110 "
b1110 &
1#
#151
0#
#152
1#
#153
0#
#154
1#
#155
0#
b1111 "
b1111 &
#156
1#
#157
0#
#158
1#
#159
0#
#160
b0 "
b0 &
1#
0$
0%
#161
0#
#162
1#
#163
0#
#164
1#
#165
0#
b1 "
b1 &
#166
1#
#167
0#
#168
1#
#169
0#
#170
b10 "
b10 &
1#
#171
0#
#172
1#
#173
0#
#174
1#
#175
0#
b11 "
b11 &
#176
1#
#177
0#
#178
1#
#179
0#
#180
b100 "
b100 &
1#
#181
0#
#182
1#
#183
0#
#184
1#
#185
0#
b101 "
b101 &
#186
1#
#187
0#
#188
1#
#189
0#
#190
b110 "
b110 &
1#
#191
0#
#192
1#
#193
0#
#194
1#
#195
0#
b111 "
b111 &
#196
1#
#197
0#
#198
1#
#199
0#
#200
b1000 "
b1000 &
1#
#201
0#
#202
1#
#203
0#
#204
1#
#205
0#
b1001 "
b1001 &
#206
1#
#207
0#
#208
1#
#209
0#
#210
b1010 "
b1010 &
1#
#211
0#
#212
1#
#213
0#
#214
1#
#215
0#
b1011 "
b1011 &
#216
1#
#217
0#
#218
1#
#219
0#
#220
b1100 "
b1100 &
1#
#221
0#
#222
1#
#223
0#
#224
1#
#225
0#
b1101 "
b1101 &
#226
1#
#227
0#
#228
1#
#229
0#
#230
b1110 "
b1110 &
1#
#231
0#
#232
1#
#233
0#
#234
1#
#235
0#
b1111 "
b1111 &
#236
1#
#237
0#
#238
1#
#239
0#
#240
b1111 !
b1111 '
b0 "
b0 &
1#
1$
#241
0#
#242
b0 !
b0 '
1#
#243
0#
#244
1#
#245
0#
b1 "
b1 &
#246
b1 !
b1 '
1#
#247
0#
#248
1#
#249
0#
#250
b10 "
b10 &
1#
#251
0#
#252
b10 !
b10 '
1#
#253
0#
#254
1#
#255
0#
b11 "
b11 &
#256
b11 !
b11 '
1#
#257
0#
#258
1#
#259
0#
#260
b100 "
b100 &
1#
#261
0#
#262
b100 !
b100 '
1#
#263
0#
#264
1#
#265
0#
b101 "
b101 &
#266
b101 !
b101 '
1#
#267
0#
#268
1#
#269
0#
#270
b110 "
b110 &
1#
#271
0#
#272
b110 !
b110 '
1#
#273
0#
#274
1#
#275
0#
b111 "
b111 &
#276
b111 !
b111 '
1#
#277
0#
#278
1#
#279
0#
#280
b1000 "
b1000 &
1#
#281
0#
#282
b1000 !
b1000 '
1#
#283
0#
#284
1#
#285
0#
b1001 "
b1001 &
#286
b1001 !
b1001 '
1#
#287
0#
#288
1#
#289
0#
#290
b1010 "
b1010 &
1#
#291
0#
#292
b1010 !
b1010 '
1#
#293
0#
#294
1#
#295
0#
b1011 "
b1011 &
#296
b1011 !
b1011 '
1#
#297
0#
#298
1#
#299
0#
#300
b1100 "
b1100 &
1#
#301
0#
#302
b1100 !
b1100 '
1#
#303
0#
#304
1#
#305
0#
b1101 "
b1101 &
#306
b1101 !
b1101 '
1#
#307
0#
#308
1#
#309
0#
#310
b1110 "
b1110 &
1#
#311
0#
#312
b1110 !
b1110 '
1#
#313
0#
#314
1#
#315
0#
b1111 "
b1111 &
#316
b1111 !
b1111 '
1#
