Ej2/Ej2.v
module Ej2(clk,Q,rst,en);
input wire clk;
input wire rst;
input wire en;
output reg Q;
initial Q = 0;
always @(posedge clk)
begin
  if (rst == 1) begin
    Q <= 0;
  end else if (rst == 0) begin
    if (en == 0) begin
      Q <= 0;
    end else if (en == 1) begin
      Q <= ~Q;
    end
  end
end
endmodule

Ej2/Ej2_tb.v
module Ej2_tb();
reg clk;
reg rst;
reg en;
wire Q;

Ej2 U1(clk,Q,rst,en);

always begin
clk = 1;
#1 clk<=~clk;
end
initial begin
$display("Clk1bit");
    $display("rst en clk | Q");
    $display("------------------------------");
    $monitor("%b %b %b | %b", rst, en, clk, Q);
  end
initial begin
 rst=1; en = 0;
 #5;
 #5;
 en = 1;
 #5;
 #5
 rst=0; en = 0;
 #5;
 #5;
 en = 1;
 #5;
end



initial
    #40 $finish;
  initial begin
    $dumpfile("Ej2_tb.vcd");
    $dumpvars(0,Ej2_tb);
  end
endmodule

Ej2/Ej2_tb.vcd
$date
	Thu Oct 29 12:20:05 2020
$end
$version
	Icarus Verilog
$end
$timescale
	1ps
$end
$scope module Ej2_tb $end
$var wire 1 ! Q $end
$var reg 1 " clk $end
$var reg 1 # en $end
$var reg 1 $ rst $end
$scope module U1 $end
$var wire 1 " clk $end
$var wire 1 # en $end
$var wire 1 $ rst $end
$var reg 1 ! Q $end
$upscope $end
$upscope $end
$enddefinitions $end
#0
$dumpvars
1$
0#
1"
0!
$end
#1
0"
#2
1"
#3
0"
#4
1"
#5
0"
#6
1"
#7
0"
#8
1"
#9
0"
#10
1"
1#
#11
0"
#12
1"
#13
0"
#14
1"
#15
0"
#16
1"
#17
0"
#18
1"
#19
0"
#20
1"
0#
0$
#21
0"
#22
1"
#23
0"
#24
1"
#25
0"
#26
1"
#27
0"
#28
1"
#29
0"
#30
1!
1"
1#
#31
0!
0"
#32
1!
1"
#33
0!
0"
#34
1!
1"
#35
0!
0"
#36
1!
1"
#37
0!
0"
#38
1!
1"
#39
0!
0"
#40
1!
1"
