Ej3/Ej3.v
module Ej3(J,K,clk,Q,rst,en);
input wire J;
input wire K;
input wire clk;
input wire rst;
input wire en;
output reg Q;
always @(posedge clk)
begin
  if (rst == 1) begin
    Q <= 0;
  end else if (rst == 0) begin
    if (en == 0) begin
      Q <= 0;
    end else if (en == 1) begin
      if(J == 0)begin
        if (K == 0) begin
          Q<=Q;
        end else if(K == 1)begin
          Q<=0;
        end
      end else if(J == 1)begin
        if(K == 0)begin
          Q<=1;
        end else if(K == 1)begin
          Q<=~Q;
        end
      end        
    end
  end
end
endmodule

Ej3/Ej3_tb.v
module Ej3_tb();
reg J;
reg K;
reg clk;
reg rst;
reg en;
wire Q;

Ej3 U1(J,K,clk,Q,rst,en);

always begin
clk = 1;
#1 clk<=~clk;
end
initial begin
$display("JKFlipFlop");
    $display("rst en clk | J K | Q");
    $display("------------------------------");
    $monitor("%b %b %b | %b %b | %b", rst, en, clk, J, K,Q);
  end
initial begin
 rst=1; en = 0;
 J <= 0; K <= 0;
 #5;
 K <= 1;
 #5;
 J <= 1;  K <= 0;
 #5;
 K <= 1;
 #5;
 en = 1;
 J <= 0; K <= 0;
 #5;
 K <= 1;
 #5;
 J <= 1;  K <= 0;
 #5;
 K <= 1;
 #5;
 rst=0; en = 0;
 J <= 0; K <= 0;
 #5;
 K <= 1;
 #5;
 J <= 1;  K <= 0;
 #5;
 K <= 1;
 #5;
 en = 1;
 J <= 0; K <= 0;
 #5;
 K <= 1;
 #5;
 J <= 1;  K <= 0;
 #5;
 K <= 1;
end



initial
    #80 $finish;
  initial begin
    $dumpfile("Ej3_tb.vcd");
    $dumpvars(0,Ej3_tb);
  end
endmodule

Ej3/Ej3_tb.vcd
$date
	Thu Oct 29 12:52:29 2020
$end
$version
	Icarus Verilog
$end
$timescale
	1ps
$end
$scope module Ej3_tb $end
$var wire 1 ! Q $end
$var reg 1 " J $end
$var reg 1 # K $end
$var reg 1 $ clk $end
$var reg 1 % en $end
$var reg 1 & rst $end
$scope module U1 $end
$var wire 1 " J $end
$var wire 1 # K $end
$var wire 1 $ clk $end
$var wire 1 % en $end
$var wire 1 & rst $end
$var reg 1 ! Q $end
$upscope $end
$upscope $end
$enddefinitions $end
#0
$dumpvars
1&
0%
1$
0#
0"
0!
$end
#1
0$
#2
1$
#3
0$
#4
1$
#5
0$
1#
#6
1$
#7
0$
#8
1$
#9
0$
#10
0#
1"
1$
#11
0$
#12
1$
#13
0$
#14
1$
#15
0$
1#
#16
1$
#17
0$
#18
1$
#19
0$
#20
0#
0"
1$
1%
#21
0$
#22
1$
#23
0$
#24
1$
#25
0$
1#
#26
1$
#27
0$
#28
1$
#29
0$
#30
0#
1"
1$
#31
0$
#32
1$
#33
0$
#34
1$
#35
0$
1#
#36
1$
#37
0$
#38
1$
#39
0$
#40
0#
0"
1$
0%
0&
#41
0$
#42
1$
#43
0$
#44
1$
#45
0$
1#
#46
1$
#47
0$
#48
1$
#49
0$
#50
0#
1"
1$
#51
0$
#52
1$
#53
0$
#54
1$
#55
0$
1#
#56
1$
#57
0$
#58
1$
#59
0$
#60
1!
0#
0"
1$
1%
#61
0$
#62
1$
#63
0$
#64
1$
#65
0$
1#
#66
0!
1$
#67
0$
#68
1$
#69
0$
#70
0#
1"
1$
#71
0$
#72
1!
1$
#73
0$
#74
1$
#75
0$
1#
#76
0!
1$
#77
0$
#78
1!
1$
#79
0$
#80
0!
1$
